<?xml version="1.0" encoding="UTF-8"?>
<record_update table="sp_css_include">
    <sp_css_include action="INSERT_OR_UPDATE">
        <name>ngTagsInputBootstrap.css</name>
        <source>local</source>
        <sp_css display_value="ng-tags-input.bootstrap.css">38afe07bb03913007f44b31da8a6d608</sp_css>
        <sys_class_name>sp_css_include</sys_class_name>
        <sys_created_by>admin</sys_created_by>
        <sys_created_on>2018-05-07 17:24:01</sys_created_on>
        <sys_id>5660f47bb03913007f44b31da8a6d68a</sys_id>
        <sys_mod_count>0</sys_mod_count>
        <sys_name>ngTagsInputBootstrap.css</sys_name>
        <sys_package display_value="Cloud Dimensions Events" source="x_snc_cloudevents">77108b70610813007f44e59882b97a67</sys_package>
        <sys_policy/>
        <sys_scope display_value="Cloud Dimensions Events">77108b70610813007f44e59882b97a67</sys_scope>
        <sys_update_name>sp_css_include_5660f47bb03913007f44b31da8a6d68a</sys_update_name>
        <sys_updated_by>admin</sys_updated_by>
        <sys_updated_on>2018-05-07 17:24:01</sys_updated_on>
        <url/>
    </sp_css_include>
</record_update>
